Envify_Cdvst/__init__.py
Envify_Cdvst-0.1.dist-info/LICENSE.txt
Envify_Cdvst-0.1.dist-info/METADATA
Envify_Cdvst-0.1.dist-info/WHEEL
Envify_Cdvst-0.1.dist-info/top_level.txt
Envify_Cdvst-0.1.dist-info/RECORD
