Metadata-Version: 2.1
Name: Envify-Cdvst
Version: 0.1
Summary: Envify
Home-page: https://now4free.de/envify_Cdvst
Author: Philpp Juen
Author-email: support@now4free.de
License-File: LICENSE.txt
